core_lib/__init__.py
core_lib/models.py
core_lib/utils.py
wheelio_assesement_core_lib-0.0.15.dist-info/METADATA
wheelio_assesement_core_lib-0.0.15.dist-info/WHEEL
wheelio_assesement_core_lib-0.0.15.dist-info/top_level.txt
wheelio_assesement_core_lib-0.0.15.dist-info/RECORD
